odoo/addons/github_connector/README.rst
odoo/addons/github_connector/__init__.py
odoo/addons/github_connector/__manifest__.py
odoo/addons/github_connector/data/ir_config_parameter.xml
odoo/addons/github_connector/data/ir_cron.xml
odoo/addons/github_connector/demo/github_organization.xml
odoo/addons/github_connector/demo/github_organization_serie.xml
odoo/addons/github_connector/models/__init__.py
odoo/addons/github_connector/models/abstract_github_model.py
odoo/addons/github_connector/models/github.py
odoo/addons/github_connector/models/github_organization.py
odoo/addons/github_connector/models/github_organization_serie.py
odoo/addons/github_connector/models/github_repository.py
odoo/addons/github_connector/models/github_repository_branch.py
odoo/addons/github_connector/models/github_team.py
odoo/addons/github_connector/models/github_team_partner.py
odoo/addons/github_connector/models/github_team_repository.py
odoo/addons/github_connector/models/res_partner.py
odoo/addons/github_connector/security/ir.model.access.csv
odoo/addons/github_connector/security/ir_model_category.xml
odoo/addons/github_connector/security/res_groups.xml
odoo/addons/github_connector/static/description/github_organization_external_services.png
odoo/addons/github_connector/static/description/github_organization_kanban.png
odoo/addons/github_connector/static/description/github_organization_series.png
odoo/addons/github_connector/static/description/github_organization_sync_buttons.png
odoo/addons/github_connector/static/description/github_repository_branch_kanban.png
odoo/addons/github_connector/static/description/github_repository_branch_list.png
odoo/addons/github_connector/static/description/github_repository_kanban.png
odoo/addons/github_connector/static/description/github_settings.png
odoo/addons/github_connector/static/description/github_team_kanban.png
odoo/addons/github_connector/static/description/github_team_partner_kanban.png
odoo11_addon_github_connector-11.0.1.1.2.dist-info/METADATA
odoo11_addon_github_connector-11.0.1.1.2.dist-info/RECORD
odoo11_addon_github_connector-11.0.1.1.2.dist-info/WHEEL
odoo11_addon_github_connector-11.0.1.1.2.dist-info/top_level.txt
